{"stats":{"minecraft:mined":{"minecraft:polished_granite_slab":312,"minecraft:cherry_log":11,"minecraft:obsidian":37,"minecraft:granite":290,"minecraft:stone_brick_wall":5,"minecraft:deepslate_bricks":8,"minecraft:hopper":3,"minecraft:oak_wall_sign":2,"minecraft:oxeye_daisy":4,"minecraft:spawner":4,"minecraft:weeping_vines_plant":3,"minecraft:polished_blackstone_bricks":93,"minecraft:tall_seagrass":5,"minecraft:magma_block":9,"minecraft:fire":157,"minecraft:cobbled_deepslate":79,"minecraft:pumpkin":2,"minecraft:deepslate_lapis_ore":11,"minecraft:oak_sign":1,"minecraft:dirt_path":46,"minecraft:oak_stairs":41,"minecraft:brown_mushroom":2,"minecraft:crimson_nylium":146,"minecraft:deepslate_brick_wall":4,"minecraft:soul_fire":1,"minecraft:powder_snow":16,"minecraft:torch":361,"minecraft:glass":47,"minecraft:sugar_cane":70,"minecraft:repeater":2,"minecraft:wheat":306,"minecraft:lilac":2,"minecraft:jukebox":1,"minecraft:stone_brick_stairs":25,"minecraft:oak_fence_gate":2,"minecraft:loom":3,"minecraft:piston":5,"minecraft:deepslate":1631,"minecraft:attached_pumpkin_stem":2,"minecraft:mossy_cobblestone":63,"minecraft:nether_bricks":95,"minecraft:cobbled_deepslate_slab":1,"minecraft:crimson_roots":15,"minecraft:redstone_wire":18,"minecraft:kelp":2,"minecraft:andesite":12959,"minecraft:potatoes":126,"minecraft:cobblestone_slab":5,"minecraft:rail":39,"minecraft:smithing_table":1,"minecraft:oak_slab":143,"minecraft:glass_pane":31,"minecraft:soul_sand":72,"minecraft:stone_brick_slab":17,"minecraft:observer":2,"minecraft:dandelion":45,"minecraft:cornflower":4,"minecraft:short_grass":778,"minecraft:emerald_ore":4,"minecraft:lightning_rod":2,"minecraft:tall_grass":163,"minecraft:copper_ore":125,"minecraft:deepslate_gold_ore":18,"minecraft:diorite":987,"minecraft:birch_leaves":2,"minecraft:sunflower":29,"minecraft:gravel":2098,"minecraft:dripstone_block":14,"minecraft:cobweb":16,"minecraft:oak_button":8,"minecraft:stone_bricks":49,"minecraft:gold_ore":24,"minecraft:spruce_planks":24,"minecraft:farmland":152,"minecraft:cobbled_deepslate_stairs":13,"minecraft:cobblestone_stairs":14,"minecraft:grass_block":10738,"minecraft:cracked_polished_blackstone_bricks":10,"minecraft:white_concrete":4,"minecraft:soul_soil":252,"minecraft:composter":4,"minecraft:gilded_blackstone":1,"minecraft:iron_ore":140,"minecraft:azure_bluet":5,"minecraft:pointed_dripstone":125,"minecraft:spruce_slab":3,"minecraft:deepslate_redstone_ore":77,"minecraft:blackstone":116,"minecraft:clay":19,"minecraft:poppy":11,"minecraft:chest":40,"minecraft:nether_quartz_ore":44,"minecraft:cobblestone":279,"minecraft:oak_planks":177,"minecraft:wall_torch":311,"minecraft:seagrass":5,"minecraft:powered_rail":1,"minecraft:nether_wart_block":37,"minecraft:birch_log":6,"minecraft:oak_log":3522,"minecraft:beetroots":83,"minecraft:sand":906,"minecraft:dirt":12680,"minecraft:netherrack":6595,"minecraft:ancient_debris":75,"minecraft:oak_leaves":603,"minecraft:nether_gold_ore":12,"minecraft:tuff":354,"minecraft:deepslate_diamond_ore":62,"minecraft:oak_door":2,"minecraft:glow_lichen":1,"minecraft:weeping_vines":4,"minecraft:polished_andesite_slab":481,"minecraft:spruce_leaves":9,"minecraft:crimson_stem":31,"minecraft:large_fern":1,"minecraft:hay_block":43,"minecraft:oak_trapdoor":25,"minecraft:spruce_sapling":14,"minecraft:carrots":165,"minecraft:gold_block":1,"minecraft:nether_brick_fence":1,"minecraft:deepslate_iron_ore":9,"minecraft:shroomlight":8,"minecraft:stripped_oak_log":77,"minecraft:packed_ice":719,"minecraft:stone":34420,"minecraft:white_tulip":1,"minecraft:redstone_wall_torch":3,"minecraft:snow_block":36,"minecraft:crafting_table":28,"minecraft:oak_fence":123,"minecraft:oak_wood":23,"minecraft:andesite_slab":18,"minecraft:lectern":23,"minecraft:andesite_wall":6,"minecraft:stone_slab":1,"minecraft:deepslate_coal_ore":12,"minecraft:lapis_ore":22,"minecraft:polished_blackstone_brick_stairs":2,"minecraft:redstone_torch":6,"minecraft:ice":10,"minecraft:yellow_bed":4,"minecraft:coal_ore":969,"minecraft:cherry_leaves":2,"minecraft:cracked_stone_bricks":1,"minecraft:polished_andesite":1170},"minecraft:picked_up":{"minecraft:lead":40,"minecraft:smithing_table":1,"minecraft:stone_slab":2,"minecraft:diamond_sword":1,"minecraft:oak_stairs":105,"minecraft:enchanted_book":1,"minecraft:golden_sword":3,"minecraft:music_disc_cat":1,"minecraft:string":158,"minecraft:soul_soil":186,"minecraft:cooked_salmon":2,"minecraft:shroomlight":8,"minecraft:beetroot":83,"minecraft:diamond_leggings":1,"minecraft:gold_nugget":88,"minecraft:cobbled_deepslate":1655,"minecraft:spruce_planks":88,"minecraft:jukebox":1,"minecraft:composter":4,"minecraft:lightning_rod":2,"minecraft:cherry_log":11,"minecraft:stone_sword":1,"minecraft:red_tulip":2,"minecraft:netherite_chestplate":1,"minecraft:blaze_rod":2,"minecraft:birch_log":6,"minecraft:magma_block":4,"minecraft:feather":15,"minecraft:cooked_beef":163,"minecraft:cherry_leaves":2,"minecraft:water_bucket":2,"minecraft:flint":4,"minecraft:netherite_leggings":1,"minecraft:lantern":8,"minecraft:diamond_helmet":1,"minecraft:ink_sac":8,"minecraft:loom":3,"minecraft:polished_andesite":1166,"minecraft:lever":1,"minecraft:polished_granite_slab":361,"minecraft:granite":304,"minecraft:bread":26,"minecraft:crimson_roots":27,"minecraft:diamond_pickaxe":3,"minecraft:spruce_leaves":3,"minecraft:crafting_table":29,"minecraft:clay_ball":8,"minecraft:leather_leggings":1,"minecraft:cornflower":5,"minecraft:glass_pane":30,"minecraft:netherite_sword":5,"minecraft:beef":21,"minecraft:poppy":12,"minecraft:spruce_slab":67,"minecraft:minecart":33,"minecraft:chest":72,"minecraft:birch_sapling":2,"minecraft:piston":5,"minecraft:egg":82,"minecraft:copper_ore":71,"minecraft:stone":31837,"minecraft:oak_door":8,"minecraft:carrot":707,"minecraft:redstone":478,"minecraft:netherite_pickaxe":6,"minecraft:tnt":2,"minecraft:diamond_chestplate":1,"minecraft:beetroot_seeds":208,"minecraft:diamond_boots":2,"minecraft:shears":1,"minecraft:deepslate_bricks":136,"minecraft:hay_block":42,"minecraft:mutton":10,"minecraft:emerald_ore":2,"minecraft:rail":57,"minecraft:white_wool":47,"minecraft:oxeye_daisy":8,"minecraft:lapis_ore":7,"minecraft:stripped_oak_log":77,"minecraft:oak_log":3762,"minecraft:ancient_debris":74,"minecraft:white_banner":2,"minecraft:stone_bricks":54,"minecraft:apple":24,"minecraft:kelp":1,"minecraft:oak_fence_gate":2,"minecraft:iron_ore":30,"minecraft:glass_bottle":2,"minecraft:iron_sword":1,"minecraft:gravel":1959,"minecraft:spruce_sapling":13,"minecraft:spruce_log":64,"minecraft:oak_wood":24,"minecraft:coal_ore":314,"minecraft:slime_ball":20,"minecraft:short_grass":1,"minecraft:diamond_axe":1,"minecraft:gray_wool":2,"minecraft:oak_button":43,"minecraft:baked_potato":2,"minecraft:crimson_nylium":79,"minecraft:hopper":27,"minecraft:ender_pearl":6,"minecraft:wheat":305,"minecraft:nether_brick_fence":1,"minecraft:potion":1,"minecraft:stone_brick_stairs":89,"minecraft:raw_copper":387,"minecraft:oak_sign":9,"minecraft:white_tulip":3,"minecraft:redstone_torch":11,"minecraft:cobblestone_slab":7,"minecraft:iron_pickaxe":1,"minecraft:furnace":3,"minecraft:stick":170,"minecraft:deepslate_brick_wall":4,"minecraft:oak_fence":127,"minecraft:torch":773,"minecraft:porkchop":2,"minecraft:snow_block":32,"minecraft:netherite_shovel":1,"minecraft:pointed_dripstone":375,"minecraft:diorite":959,"minecraft:andesite_wall":3,"minecraft:rotten_flesh":298,"minecraft:obsidian":37,"minecraft:cobblestone":2524,"minecraft:leather_chestplate":1,"minecraft:lilac":2,"minecraft:repeater":2,"minecraft:andesite":12922,"minecraft:golden_leggings":1,"minecraft:potato":469,"minecraft:tuff":252,"minecraft:wither_skeleton_skull":2,"minecraft:lapis_lazuli":330,"minecraft:dirt":9169,"minecraft:glass":45,"minecraft:bone":639,"minecraft:bow":38,"minecraft:wheat_seeds":1107,"minecraft:cobbled_deepslate_slab":1,"minecraft:raw_gold":82,"minecraft:netherite_axe":2,"minecraft:powered_rail":1,"minecraft:oak_planks":251,"minecraft:cooked_porkchop":376,"minecraft:music_disc_13":3,"minecraft:oak_pressure_plate":1,"minecraft:poisonous_potato":1,"minecraft:sand":888,"minecraft:grass_block":9228,"minecraft:spectral_arrow":10,"minecraft:mossy_cobblestone":63,"minecraft:clay":17,"minecraft:diamond":133,"minecraft:netherite_helmet":1,"minecraft:cracked_polished_blackstone_bricks":10,"minecraft:crossbow":1,"minecraft:white_concrete":118,"minecraft:emerald":2,"minecraft:oak_sapling":146,"minecraft:netherrack":4363,"minecraft:oak_leaves":614,"minecraft:andesite_slab":19,"minecraft:azure_bluet":6,"minecraft:chicken":5,"minecraft:chest_minecart":2,"minecraft:packed_ice":602,"minecraft:stone_brick_wall":5,"minecraft:gold_block":1,"minecraft:oak_trapdoor":22,"minecraft:blackstone":103,"minecraft:oak_boat":49,"minecraft:observer":2,"minecraft:light_gray_wool":4,"minecraft:lectern":23,"minecraft:sugar_cane":119,"minecraft:phantom_membrane":7,"minecraft:raw_iron":248,"minecraft:polished_blackstone_bricks":82,"minecraft:stone_button":2,"minecraft:arrow":799,"minecraft:weeping_vines":3,"minecraft:nether_bricks":85,"minecraft:pink_tulip":3,"minecraft:saddle":2,"minecraft:netherite_boots":1,"minecraft:glow_ink_sac":13,"minecraft:crimson_stem":28,"minecraft:leather":106,"minecraft:ice":10,"minecraft:crimson_fungus":5,"minecraft:yellow_bed":5,"minecraft:nether_wart_block":31,"minecraft:cobbled_deepslate_stairs":13,"minecraft:gunpowder":164,"minecraft:cobblestone_stairs":12,"minecraft:cooked_mutton":72,"minecraft:rabbit_hide":1,"minecraft:iron_ingot":18,"minecraft:cooked_chicken":14,"minecraft:polished_andesite_slab":494,"minecraft:soul_sand":54,"minecraft:oak_slab":338,"minecraft:pumpkin":2,"minecraft:stone_brick_slab":15,"minecraft:quartz":101,"minecraft:dandelion":97,"minecraft:dripstone_block":11,"minecraft:spider_eye":47,"minecraft:pumpkin_seeds":4,"minecraft:black_wool":4,"minecraft:netherite_hoe":1,"minecraft:coal":1401,"minecraft:sunflower":44},"minecraft:used":{"minecraft:spruce_slab":186,"minecraft:dispenser":1,"minecraft:ladder":12,"minecraft:chest":82,"minecraft:stone":32601,"minecraft:soul_sand":3,"minecraft:azure_bluet":3,"minecraft:packed_ice":276,"minecraft:lava_bucket":1,"minecraft:netherite_shovel":20013,"minecraft:grass_block":4001,"minecraft:copper_ore":57,"minecraft:netherite_hoe":69,"minecraft:stone_brick_stairs":325,"minecraft:bow":652,"minecraft:egg":89,"minecraft:potato":110,"minecraft:deepslate_brick_wall":4,"minecraft:diorite":60,"minecraft:powered_rail":34,"minecraft:blackstone":21,"minecraft:composter":5,"minecraft:clay":2,"minecraft:oak_leaves":338,"minecraft:sand":131,"minecraft:lightning_rod":1,"minecraft:stone_button":57,"minecraft:lectern":28,"minecraft:polished_andesite_slab":3374,"minecraft:diamond_sword":1604,"minecraft:smithing_table":3,"minecraft:oak_boat":51,"minecraft:oak_trapdoor":171,"minecraft:iron_bars":24,"minecraft:netherrack":1700,"minecraft:torch":2531,"minecraft:anvil":5,"minecraft:stone_stairs":4,"minecraft:polished_granite_slab":583,"minecraft:oak_fence_gate":8,"minecraft:chipped_anvil":1,"minecraft:iron_axe":662,"minecraft:chicken_spawn_egg":21,"minecraft:cobbled_deepslate":725,"minecraft:observer":18,"minecraft:pointed_dripstone":363,"minecraft:wheat_seeds":169,"minecraft:water_bucket":181,"minecraft:sheep_spawn_egg":15,"minecraft:deepslate_bricks":8,"minecraft:polished_blackstone_bricks":82,"minecraft:rail":159,"minecraft:oak_slab":2061,"minecraft:crafting_table":27,"minecraft:birch_sign":3,"minecraft:white_bed":11,"minecraft:campfire":2,"minecraft:oak_log":5241,"minecraft:ender_eye":1,"minecraft:diamond_pickaxe":24086,"minecraft:oxeye_daisy":52,"minecraft:diamond_shovel":7257,"minecraft:oak_button":130,"minecraft:spruce_trapdoor":18,"minecraft:spruce_sapling":61,"minecraft:crimson_nylium":64,"minecraft:cobblestone":865,"minecraft:cooked_porkchop":300,"minecraft:andesite_stairs":20,"minecraft:glass_pane":131,"minecraft:stripped_oak_log":436,"minecraft:dandelion":17,"minecraft:jukebox":2,"minecraft:diamond_hoe":71,"minecraft:oak_sign":27,"minecraft:spruce_leaves":3,"minecraft:nether_bricks":44,"minecraft:carrot":244,"minecraft:tuff":24,"minecraft:music_disc_13":1,"minecraft:obsidian":32,"minecraft:glass":236,"minecraft:coal_ore":311,"minecraft:stone_bricks":229,"minecraft:item_frame":1,"minecraft:repeater":4,"minecraft:beetroot_seeds":78,"minecraft:dropper":1,"minecraft:oak_planks":502,"minecraft:ender_pearl":2,"minecraft:diamond_axe":4439,"minecraft:sugar_cane":35,"minecraft:loom":1,"minecraft:black_bed":1,"minecraft:stone_brick_wall":58,"minecraft:shears":174,"minecraft:cobbled_deepslate_stairs":32,"minecraft:redstone_torch":22,"minecraft:sticky_piston":1,"minecraft:lever":2,"minecraft:bread":145,"minecraft:gravel":1104,"minecraft:grindstone":1,"minecraft:andesite":1737,"minecraft:chest_minecart":3,"minecraft:white_concrete":174,"minecraft:bone_meal":274,"minecraft:oak_fence":524,"minecraft:netherite_sword":2115,"minecraft:flint_and_steel":14,"minecraft:redstone":42,"minecraft:spruce_planks":2919,"minecraft:cooked_chicken":3,"minecraft:oak_door":21,"minecraft:dirt":4014,"minecraft:hopper":31,"minecraft:spruce_stairs":5,"minecraft:oak_wood":57,"minecraft:granite":21,"minecraft:andesite_wall":41,"minecraft:stone_brick_slab":175,"minecraft:bookshelf":34,"minecraft:oak_stairs":1358,"minecraft:golden_carrot":72,"minecraft:soul_soil":177,"minecraft:netherite_pickaxe":38918,"minecraft:minecart":28,"minecraft:cooked_beef":149,"minecraft:light_gray_bed":1,"minecraft:cooked_mutton":56,"minecraft:iron_ore":26,"minecraft:cobblestone_stairs":202,"minecraft:snow_block":32,"minecraft:polished_andesite":11207,"minecraft:andesite_slab":248,"minecraft:stonecutter":1,"minecraft:cobblestone_slab":38,"minecraft:music_disc_cat":1,"minecraft:piston":21,"minecraft:flower_pot":1,"minecraft:netherite_axe":505,"minecraft:lapis_ore":7,"minecraft:stone_slab":56,"minecraft:cobbled_deepslate_slab":13,"minecraft:bucket":183,"minecraft:yellow_bed":3},"minecraft:custom":{"minecraft:interact_with_crafting_table":372,"minecraft:bell_ring":8,"minecraft:leave_game":124,"minecraft:time_since_death":493654,"minecraft:play_time":6671726,"minecraft:deaths":1,"minecraft:jump":80339,"minecraft:enchant_item":61,"minecraft:interact_with_furnace":541,"minecraft:play_record":2,"minecraft:traded_with_villager":58,"minecraft:sleep_in_bed":103,"minecraft:damage_dealt":269361,"minecraft:interact_with_smithing_table":17,"minecraft:inspect_dispenser":12,"minecraft:inspect_dropper":2,"minecraft:interact_with_anvil":74,"minecraft:inspect_hopper":6,"minecraft:sneak_time":145974,"minecraft:total_world_time":6671726,"minecraft:interact_with_stonecutter":20,"minecraft:time_since_rest":42084,"minecraft:swim_one_cm":999960,"minecraft:fly_one_cm":19380003,"minecraft:open_chest":3381,"minecraft:fall_one_cm":2123515,"minecraft:animals_bred":171,"minecraft:sprint_one_cm":14576416,"minecraft:drop":636,"minecraft:talked_to_villager":82,"minecraft:walk_on_water_one_cm":582448,"minecraft:interact_with_loom":1,"minecraft:player_kills":6,"minecraft:crouch_one_cm":652707,"minecraft:mob_kills":3529,"minecraft:climb_one_cm":279041,"minecraft:walk_one_cm":15731159,"minecraft:walk_under_water_one_cm":419974,"minecraft:boat_one_cm":1646096,"minecraft:pot_flower":1,"minecraft:interact_with_grindstone":6,"minecraft:damage_taken":20546,"minecraft:minecart_one_cm":698679},"minecraft:dropped":{"minecraft:lapis_lazuli":10,"minecraft:cooked_beef":61,"minecraft:emerald_ore":2,"minecraft:diamond":2,"minecraft:cooked_porkchop":23,"minecraft:weeping_vines":3,"minecraft:saddle":2,"minecraft:emerald":1,"minecraft:dirt":1459,"minecraft:gold_nugget":8,"minecraft:bone_block":10,"minecraft:sunflower":1,"minecraft:bone":199,"minecraft:oak_door":1,"minecraft:iron_nugget":8,"minecraft:cooked_chicken":1,"minecraft:cobbled_deepslate":185,"minecraft:netherite_sword":4,"minecraft:wheat":1,"minecraft:obsidian":1,"minecraft:rotten_flesh":38,"minecraft:coal_ore":3,"minecraft:hopper":2,"minecraft:leather_leggings":1,"minecraft:white_dye":6,"minecraft:egg":1,"minecraft:enchanted_book":1,"minecraft:netherite_pickaxe":2,"minecraft:wheat_seeds":98,"minecraft:cobbled_deepslate_stairs":3,"minecraft:feather":2,"minecraft:cobblestone":99,"minecraft:granite":29,"minecraft:polished_andesite":1,"minecraft:oxeye_daisy":1,"minecraft:golden_carrot":1,"minecraft:diamond_helmet":1,"minecraft:string":27,"minecraft:pink_tulip":2,"minecraft:netherite_ingot":1,"minecraft:cobbled_deepslate_slab":36,"minecraft:oak_sign":1,"minecraft:shears":1,"minecraft:diamond_sword":1,"minecraft:stone":1,"minecraft:diamond_pickaxe":3,"minecraft:redstone_torch":1,"minecraft:spider_eye":5,"minecraft:bow":219,"minecraft:crimson_nylium":10,"minecraft:soul_sand":1,"minecraft:diamond_axe":1,"minecraft:oak_log":64,"minecraft:netherite_upgrade_smithing_template":1,"minecraft:leather":10,"minecraft:flint":1,"minecraft:packed_ice":7,"minecraft:cornflower":1,"minecraft:crimson_roots":17,"minecraft:gravel":7,"minecraft:crimson_fungus":4,"minecraft:andesite_slab":1,"minecraft:cooked_mutton":1,"minecraft:carrot":316,"minecraft:poppy":4,"minecraft:leather_chestplate":1,"minecraft:gunpowder":15,"minecraft:chest":4,"minecraft:iron_ore":3,"minecraft:arrow":248,"minecraft:quartz":14,"minecraft:oak_leaves":2,"minecraft:netherrack":441,"minecraft:water_bucket":1,"minecraft:bread":15,"minecraft:diamond_leggings":1,"minecraft:lead":2,"minecraft:spectral_arrow":10,"minecraft:grass_block":1279,"minecraft:stick":7,"minecraft:torch":3,"minecraft:nether_wart_block":2,"minecraft:dandelion":65,"minecraft:redstone":53,"minecraft:kelp":1,"minecraft:oak_trapdoor":1,"minecraft:raw_copper":24,"minecraft:raw_iron":5,"minecraft:flint_and_steel":1,"minecraft:deepslate_bricks":128,"minecraft:copper_ore":10,"minecraft:oak_button":1,"minecraft:diamond_chestplate":1,"minecraft:andesite":3,"minecraft:golden_leggings":2,"minecraft:golden_sword":2,"minecraft:diamond_boots":2},"minecraft:broken":{"minecraft:iron_axe":2},"minecraft:killed":{"minecraft:cave_spider":3,"minecraft:skeleton":2258,"minecraft:chicken":16,"minecraft:magma_cube":14,"minecraft:salmon":1,"minecraft:iron_golem":2,"minecraft:pillager":9,"minecraft:zombie":305,"minecraft:glow_squid":2,"minecraft:cow":59,"minecraft:wandering_trader":2,"minecraft:enderman":13,"minecraft:witch":7,"minecraft:spider":145,"minecraft:piglin_brute":2,"minecraft:wolf":2,"minecraft:piglin":60,"minecraft:pig":68,"minecraft:zombie_villager":6,"minecraft:creeper":161,"minecraft:sheep":54,"minecraft:trader_llama":14,"minecraft:ghast":4,"minecraft:blaze":6,"minecraft:slime":28,"minecraft:phantom":9,"minecraft:drowned":6,"minecraft:hoglin":52,"minecraft:squid":4,"minecraft:wither_skeleton":12,"minecraft:villager":1},"minecraft:crafted":{"minecraft:oak_sign":15,"minecraft:blaze_powder":4,"minecraft:lever":1,"minecraft:diamond_shovel":1,"minecraft:bookshelf":12,"minecraft:cooked_mutton":4,"minecraft:iron_bars":48,"minecraft:glass":378,"minecraft:repeater":2,"minecraft:netherite_boots":1,"minecraft:flower_pot":1,"minecraft:emerald":185,"minecraft:cooked_porkchop":1,"minecraft:chest_minecart":1,"minecraft:raw_gold_block":4,"minecraft:smithing_table":2,"minecraft:copper_ingot":375,"minecraft:sticky_piston":1,"minecraft:oak_wood":51,"minecraft:hay_block":33,"minecraft:campfire":2,"minecraft:light_gray_bed":1,"minecraft:stone_brick_stairs":200,"minecraft:lectern":6,"minecraft:stone_slab":12,"minecraft:iron_block":35,"minecraft:gold_ingot":161,"minecraft:netherite_ingot":18,"minecraft:composter":2,"minecraft:golden_carrot":73,"minecraft:jukebox":1,"minecraft:bone_meal":240,"minecraft:andesite_wall":60,"minecraft:stone_stairs":4,"minecraft:diamond":18,"minecraft:netherite_axe":1,"minecraft:ladder":6,"minecraft:spruce_slab":186,"minecraft:cobbled_deepslate_stairs":48,"minecraft:redstone_block":56,"minecraft:wheat":594,"minecraft:coal_block":115,"minecraft:netherite_pickaxe":3,"minecraft:enchanted_book":5,"minecraft:oak_fence_gate":6,"minecraft:andesite_slab":288,"minecraft:oak_stairs":380,"minecraft:white_bed":14,"minecraft:brick":8,"minecraft:grindstone":1,"minecraft:oak_planks":2440,"minecraft:cobblestone_slab":12,"minecraft:polished_granite_slab":492,"minecraft:stone":456,"minecraft:cobblestone_stairs":512,"minecraft:hopper":1,"minecraft:stone_brick_slab":192,"minecraft:raw_copper":27,"minecraft:chest":5,"minecraft:netherite_helmet":1,"minecraft:oak_button":35,"minecraft:copper_block":68,"minecraft:netherite_upgrade_smithing_template":8,"minecraft:rail":304,"minecraft:ender_eye":4,"minecraft:stone_bricks":712,"minecraft:oak_fence":279,"minecraft:raw_iron_block":5,"minecraft:dropper":1,"minecraft:oak_slab":1110,"minecraft:item_frame":1,"minecraft:arrow":12,"minecraft:crafting_table":3,"minecraft:spruce_planks":2564,"minecraft:gold_block":27,"minecraft:birch_planks":16,"minecraft:dispenser":1,"minecraft:spruce_trapdoor":20,"minecraft:book":34,"minecraft:paper":174,"minecraft:diamond_pickaxe":10,"minecraft:emerald_block":16,"minecraft:stick":848,"minecraft:netherite_hoe":1,"minecraft:iron_ingot":409,"minecraft:andesite_stairs":32,"minecraft:black_bed":1,"minecraft:redstone_torch":36,"minecraft:shears":2,"minecraft:polished_andesite":5004,"minecraft:oak_door":12,"minecraft:cobbled_deepslate_slab":48,"minecraft:redstone":81,"minecraft:raw_iron":45,"minecraft:coal":171,"minecraft:stone_brick_wall":54,"minecraft:netherite_sword":1,"minecraft:stone_button":60,"minecraft:piston":22,"minecraft:polished_andesite_slab":2880,"minecraft:raw_copper_block":3,"minecraft:oak_trapdoor":134,"minecraft:glass_pane":144,"minecraft:diamond_block":10,"minecraft:flint_and_steel":2,"minecraft:netherite_chestplate":1,"minecraft:netherite_leggings":1,"minecraft:iron_axe":4,"minecraft:netherite_scrap":74,"minecraft:birch_sign":3,"minecraft:observer":16,"minecraft:minecart":12,"minecraft:cooked_beef":77,"minecraft:bone_block":10,"minecraft:powered_rail":48,"minecraft:bucket":1,"minecraft:bread":125,"minecraft:air":0,"minecraft:oak_boat":6,"minecraft:gold_nugget":567,"minecraft:white_dye":6,"minecraft:raw_gold":36,"minecraft:stonecutter":1,"minecraft:anvil":4,"minecraft:torch":1556,"minecraft:lapis_lazuli":18,"minecraft:lapis_block":47}},"DataVersion":3839}